reticle_pipeline/__init__.py
reticle_pipeline/utils.py
reticle_pipeline-0.0.6.dist-info/METADATA
reticle_pipeline-0.0.6.dist-info/WHEEL
reticle_pipeline-0.0.6.dist-info/RECORD
