Metadata-Version: 2.4
Name: reticle_pipeline
Version: 0.0.6
Summary: Reticle pipeline
Project-URL: Homepage, https://github.com/brauchilab/Python-Fiji-Pipeline
Author-email: Alvaro <a.navarrogg@gmail.com>
License: MIT
Classifier: Operating System :: OS Independent
Classifier: Programming Language :: Python :: 3
Requires-Python: >=3.8
